## 虚方法和非虚方法

* 如果方法在编译期就确定了具体的调用版本，这个版本在运行时是不可变的。这样的方法称为非虚方法。

* 静态方法、私有方法、final方法、实例构造器、父类方法都是非虚方法。
* 其他方法称为虚方法。



## 普通调用指令

- <font color="cyan">invokestatic：调用静态方法，解析阶段确定唯一方法版本</font>

- <font color="cyan">invokespecial：调用方法、私有及父类方法，解析阶段确定唯一方法版本</font>

- invokevirtual：调用所有虚方法

- invokeinterface：调用接口方法

这四条指令固化在虚拟机内部，方法的调用执行不可人为干预，<font color="orange">其中invokestatic指令和invokespecial指令调用的方法称为非虚方法，其余的（final修饰的除外）称为虚方法。</font>

### 例子

```java
class Father {
    public Father() {
        System.out.println("father的构造器");
    }

    public static void showStatic(String str) {
        System.out.println("father " + str);
    }

    public final void showFinal() {
        System.out.println("father show final");
    }

    public void showCommon() {
        System.out.println("father 普通方法");
    }
}

public class Son extends Father {

    public static void main(String[] args) {
        Son so = new Son();
        so.show();
    }

    public Son() {
        // 子类构造器调用父类无参构造，属于非虚方法【invokespecial】
        super();
    }

    public Son(int age) {
        // 有参调用无参，属于非虚方法【invokespecial】
        this();
    }

    //不是重写的父类的静态方法，因为静态方法不能被重写！只不过方法名一样了而已
    public static void showStatic(String str) {
        System.out.println("son " + str);
    }

    private void showPrivate(String str) {
        System.out.println("son private" + str);
    }

    public void info() {

    }

    public void display(Father f) {
        f.showCommon();
    }

    public void show() {
        // 有static，非虚方法 【invokestatic】
        showStatic("atguigu.com");

        // 明确了是父类的方法，非虚方法【invokestatic】
        super.showStatic("good!");

        //调用了私有方法，也是非虚方法【invokespecial】
        showPrivate("hello!");

        //明确了是父类的方法，非虚方法【invokespecial】
        super.showCommon();

        // 父类的这个方法被final修饰，不能被子类重写，所以也是非虚方法【invokevirtual】
        showFinal();


        // 没有super，并且不是static，也不是final，也不是private，
        // 如果这个类被继承，Son的子类去重写了这个方法，那么就是多态
        // 因此编译期间确定不了，是虚方法【invokevirtual】
        showCommon();
        // 同上，是虚方法【invokevirtual】
        info();

        // 接口实现类的方法，因此在编译期间也无法确定下来
        // 是虚方法【invokeinterface】
        MethodInterface in = null;
        in.methodA();
    }

}

interface MethodInterface {
    void methodA();
}
```



## 动态调用指令

* invokedynamic：动态解析出需要调用的方法，然后执行

### 概念

* invokedynamic指令则支持由用户确定方法版本
* JVM字节码指令集一直比较稳定，一直到Java7中才增加了一个invokedynamic指令，这是<font color="orange">Java为了实现【动态类型语言】支持而做的一种改进</font>。
* 但是在Java7中并没有提供直接生成invokedynamic指令的方法，需要借助ASM这种底层字节码工具来产生invokedynamic指令。<font color="cyan">直到Java8的Lambda表达式的出现，invokedynamic指令的生成，在Java中才有了直接的生成方式</font>。
* Java7中增加的动态语言类型支持的本质是对Java虚拟机规范的修改，而不是对Java语言规则的修改，这一块相对来讲比较复杂，增加了虚拟机中的方法调用，最直接的受益者就是运行在Java平台的动态语言的编译器。

### 动态语言和静态语言

* 动态类型语言和静态类型语言两者的区别就在于**对类型的检查是在编译期还是在运行期**，满足前者就是静态类型语言，反之是动态类型语言。
* 说的再直白一点就是，<font color="cyan">静态类型语言是判断变量自身的类型信息；动态类型语言是判断变量值的类型信息，变量没有类型信息，变量值才有类型信息</font>，这是动态语言的一个重要特征。
* java语言仍然是静态语言，但有了invokedynamic，有了动态语言的一些特性

例如下面的java代码，就是需要在编译期就确定类型

```java
String info = "static"
```

而Python就不需要，他是在运行时判断类型

```python
info = 130.5
```

### invokedynamic 例子

```java
@FunctionalInterface
interface Func {
    public boolean func(String str);
}

public class Lambda {
    public void method(Func func) {
        return;
    }

    public static void main(String[] args) {
        Lambda lambda = new Lambda();
        // 生成接口对象
        Func func = s -> {
            return true;
        };
        lambda.method(func);

        // 生成接口匿名对象
        lambda.method(s -> {
            return true;
        });
    }
}
// --------------- 字节码 ---------------
 0 new #2 <com/cloud/Lambda>
 3 dup
 4 invokespecial #3 <com/cloud/Lambda.<init> : ()V>
 7 astore_1
 8 invokedynamic #4 <func, BootstrapMethods #0> // 这里
13 astore_2
14 aload_1
15 aload_2
16 invokevirtual #5 <com/cloud/Lambda.method : (Lcom/cloud/Func;)V>
19 aload_1
20 invokedynamic #6 <func, BootstrapMethods #1> // 还有这里
25 invokevirtual #5 <com/cloud/Lambda.method : (Lcom/cloud/Func;)V>
28 return
```

