```java
class Father {
    int x = 10;

    public Father() { // 3. 调用父类的构造
        this.print(); // 4. 执行print方法，由于是在子类中调用print方法，优先看子类是否有这个print方法，没有才会调用父类的方法
        x = 20; // 7.这个x是facher的x，到这里就代表father初始化完成，去执行子类的初始化
    }
    public void print() {
        System.out.println("Father.x = " + x);
    }
}

class Son extends Father {
    int x = 30; // 8.子类开始显式初始化
    public Son() { // 2.子类初始化之前会先初始化父类
        this.print(); // 9. 执行print方法，经过上面的显式初始化，现在的x = 30
        x = 40; // 10.现在son.x = 40
    }
    public void print() { // 5.子类有这个print方法，执行
        System.out.println("Son.x = " + x); // 6.我们的son还没开始显式始化，就先执行了print，所以son.x = 0
    }
}

public class SonTest {
    public static void main(String[] args) {
        Father f = new Son(); // 1.开始son的初始化操作
        System.out.println(f.x); // 11.再次执行son的x，son.x = 40
    }
}
```

```java
Son.x = 0
Son.x = 30
20
```

成员变量（非静态的）的赋值过程： 

1. 默认初始化

2. 显式初始化 /代码块中初始化

3. 构造器中初始化 

4. 有了对象之后，可以“对象.属性”或"对象.方法"





## 通过字节码查看

### main方法的字节码

```java
 0 new #2 <com/cloud/java/Son>
 3 dup
 4 invokespecial #3 <com/cloud/java/Son.<init> : ()V>
 7 astore_1
 8 getstatic #4 <java/lang/System.out : Ljava/io/PrintStream;>
11 aload_1
12 getfield #5 <com/cloud/java/Father.x : I>
15 invokevirtual #6 <java/io/PrintStream.println : (I)V>
18 return
```

### son的字节码

```java
 0 aload_0
 1 invokespecial #1 <com/cloud/java/Father.<init> : ()V>
 4 aload_0
 5 bipush 30
 7 putfield #2 <com/cloud/java/Son.x : I>
10 aload_0
11 invokevirtual #3 <com/cloud/java/Son.print : ()V>
14 aload_0
15 bipush 40
17 putfield #2 <com/cloud/java/Son.x : I>
20 return
```

### facher的字节码

```java
 0 aload_0
 1 invokespecial #1 <java/lang/Object.<init> : ()V>
 4 aload_0
 5 bipush 10
 7 putfield #2 <com/cloud/java/Father.x : I>
10 aload_0
11 invokevirtual #3 <com/cloud/java/Father.print : ()V>
14 aload_0
15 bipush 20
17 putfield #2 <com/cloud/java/Father.x : I>
20 return
```

