## 作用

算术指令用于对两个操作数栈上的值进行某种特定运算，并把结果重新压入操作数栈。

## 分类

大体上算术指令可以分为两种：对<font color="orange">整型数据</font>进行运算的指令与对<font color="orange">浮点类型数据</font>进行运算的指令。

## byte、short、char和boolean类型说明

在每一大类中，都有针对Java虚拟机具体数据类型的专用算术指令。但没有直接支持byte、short、char和boolean类型的算术指令，对于这些数据的运算，都使用int类型的指令来处理。此外，在处理boolean、byte、short和char类型的数组时，也会转换为使用对应的int类型的字节码指令来处理。

|   实际类型    |   运算类型    | 分类 |
| :-----------: | :-----------: | :--: |
|    boolean    |      int      |  一  |
|     byte      |      int      |  一  |
|     char      |      int      |  一  |
|     short     |      int      |  一  |
|      int      |      int      |  一  |
|     float     |     float     |  一  |
|   reference   |   reference   |  一  |
| returnAddress | returnAddress |  一  |
|     long      |     long      |  二  |
|    double     |    double     |  二  |

## 运算时的溢出

数据运算可能会导致溢出，例如两个很大的正整数相加，结果可能是一个负数。其实Java虚拟机规范并无明确规定过整型数据溢出的具体结果，仅规定了在处理整型数据时，只有除法指令以及求余指令中当出现除数为0时会导致虚拟机抛出异常ArithmeticException。

## 运算模式

**向最接近数舍入模式**：JVM要求在进行浮点数计算时，所有的运算结果都必须舍入到适当的精度，非精确结果必须舍入为可被表示的最接近的精确值，如果有两种可表示的形式与该值一样接近，将优先选择最低有效位为零的；

**向零舍入模式**：将浮点数转换为整数时，采用该模式，该模式将在目标数值类型中选择一个最接近但是不大于原值的数字作为最精确的舍入结果；

## NaN值使用

当一个操作产生溢出时，将会使用有符号的无穷大表示，如果某个操作结果没有明确的数学定义的话，将会使用NaN值来表示。而且所有使用NaN值作为操作数的算术操作，结果都会返回NaN；

```java
double j = 10 / 0.0;
System.out.println(j); // Infinity【无穷大】
double d2 = 0.0 / 0.0;
System.out.println(d2); // NaN: not a number
```

## 所有的算术指令

- 加法指令：iadd、ladd、fadd、dadd
- 减法指令：isub、lsub、fsub、dsub
- 乘法指令：imul、lmul、fmul、dmul
- 除法指令：idiv、ldiv、fdiv、ddiv
- 求余指令：irem、lrem、frem、drem（remainder：余数）
- 取反指令：ineg、lneg、fneg、dneg（negation：取反）
- 自增指令：iinc
- 位运算指令，又可分为：
  - 位移指令：ishl【左移】、ishr【右移】、iushr【无符号右移】、lshl、lshr、lushr
  - 按位或指令：ior、lor
  - 按位与指令：iand、land
  - 按位异或指令：ixor、lxor
- 比较指令：dcmpg、dcmlp、fcmpg、fcmpl、lcmp

### 异或

```java
public int method5(int i ,int j){
    return ((i + j - 1) & ~(j - 1));
}
```

```java
 0 iload_1
 1 iload_2
 2 iadd
 3 iconst_1
 4 isub
 5 iload_2
 6 iconst_1
 7 isub
 8 iconst_m1
 9 ixor
10 iand
11 ireturn
```

这里的异或是-1和需要取反的数做异或操作
具体参考https://blog.csdn.net/weixin_41165867/article/details/103446134
-128~127的来源：https://blog.csdn.net/zhangjin1120/article/details/81274647

## 算术运算符的举例

参考 [15.操作数栈.md](./15.操作数栈) 和 [39.方法区使用举例.md](39.方法区使用举例.md)



## i++ 和 ++i的爱恨情仇

```java
public void method7(){
    int i = 10;
    int a = i++; // 10
    int j = 20;
    int b = ++j; // 21
}
```

```java
 0 bipush 10
 2 istore_1
 3 iload_1
 4 iinc 1 by 1
 7 istore_2
     
 8 bipush 20
10 istore_3
11 iinc 3 by 1
14 iload_3
15 istore 4
     
17 return
```

我们拆成2部分看，

第一个i++，你看先放到操作数栈中，然后再对原有数据做累加，这样i变成了11，而a还是10

第二个++i，是先累加，然后再放到操作数栈中，因此j是21，b也是21



那我们再看下面这个例子

```java
int i = 10;
i = i++;
System.out.println(i); // 10
```

```java
 0 bipush 10
 2 istore_1
 3 iload_1
 4 iinc 1 by 1
 7 istore_1
 8 getstatic #4 <java/lang/System.out : Ljava/io/PrintStream;>
11 iload_1
12 invokevirtual #9 <java/io/PrintStream.println : (I)V>
15 return
```

你看，先放到操作数栈，然后对i++，但是！

操作数栈中的10放回局部变量表的时候，把原有的i++覆盖了，然后导致i还是10





## 比较指令的说明

- 比较指令的作用是比较栈顶两个元素的大小，并将比较结果入栈
- 比较指令有：<font color="orange">dcmpg、dcmpl、fcmpg、fcmpl、lcmp</font>
  - 与前面讲解的指令类似，首字符 d 表示 double 类型，f 表示 float，l 表示 long
- 对于 double 和 float 类型的数字，由于 NaN 的存在，各有两个版本的比较指令，以 float 为例，有 fcmpg 和 fcmpl 两个指令，它们的区别在于在数字比较时，若遇到 NaN 值，处理结果不同
- 指令 dcmpl 和 dcmpg 也是类似的，根据其命名可以推测其含义，在此不再赘述
- 指令 lcmp 针对 long 型整数，由于 long 型整数没有 NaN 值，故无需准备两套指令

举例：

指令 fcmpg 和 fcmpl 都从栈中弹出两个操作数，并将它们做比较，设栈顶的元素为 v2， 栈顶顺位第 2 位元素为 v1，若 v1 = v2，则压入 0；若 v1 > v2 则压入 1；若 v1 < v2 则压入 -1。

两个指令的不同之处在于，如果遇到 NaN 值，fcmpg 会压入 1，而 fcmpl 会压入 -1。

> 数值类型的数据才可以谈大小，boolean、引用数据类型不能比较大小。