## 概述

<font color="cyan">这个只用于int类型和引用类型比较</font>

比较条件跳转指令类似于比较指令和条件跳转指令的结合体，它将比较和跳转两个步骤合二为一。

这类指令有：if_icmpeq、if_icmpne、if_icmplt、if_icmpgt、if_icmple、if_icmpge、if_acmpeq和if_acmpne。其中指令助记符加上“if_”后，以字符“i”开头的指令针对it型整数操作（也包括short和byte类型），以字符“a”开头的指令表示对象引用的比较。

|   指令    | 符号 |                        说明                         |
| :-------: | :--: | :-------------------------------------------------: |
| if_acmpeq |  ==  |   比较栈顶俩int类型数值大小，当前者等于后者时跳转   |
| if_icmpne |  !=  |  比较栈顶俩int类型数值大小，当前者不等于后者时跳转  |
| if_icmplt |  <   |   比较栈顶俩int类型数值大小，当前者小于后者时跳转   |
| if_icmple |  <=  | 比较栈顶俩int类型数值大小，当前者小于等于后者时跳转 |
| if_icmpgt |  >   |   比较栈顶俩int类型数值大小，当前者大于后者时跳转   |
| if_icmpge |  >=  | 比较栈顶俩int类型数值大小，当前者大于等于后者时跳转 |
| if_icmpeq |  ==  |      比较栈顶俩引用类型数值，当结果相等时跳转       |
| if_icmpne |  !=  |     比较栈顶俩引用类型数值，当结果不相等时跳转      |

这些指令都接收两个字节的操作数作为参数，用于计算跳转的位置。同时在执行指令时，栈顶需要准备两个元素进行比较。指令执行完成后，栈顶的这两个元素被清空，且没有任何数据入栈。<font color="orange">如果预设条件成立，则执行跳转，否则，继续执行下一条语句。</font>



## 例子一

```java
int i = 10;
int j = 20;
System.out.println(i > j);
```

```java
 0 bipush 10
 2 istore_1
 3 bipush 20
 5 istore_2
 6 getstatic #4 <java/lang/System.out : Ljava/io/PrintStream;>
 9 iload_1
10 iload_2
11 if_icmple 18 (+7)  // 10 <= 20
14 iconst_1
15 goto 19 (+4)
18 iconst_0
19 invokevirtual #5 <java/io/PrintStream.println : (Z)V>
22 return
```



## 例子二

```java
short s1 = 9;
byte b1 = 10;
System.out.println(s1 > b1);
```

```java
 0 bipush 9
 2 istore_1
 3 bipush 10
 5 istore_2
 6 getstatic #4 <java/lang/System.out : Ljava/io/PrintStream;>
 9 iload_1
10 iload_2
11 if_icmple 18 (+7) // 9 <= 10
14 iconst_1
15 goto 19 (+4)
18 iconst_0 // false
19 invokevirtual #5 <java/io/PrintStream.println : (Z)V>
22 return
```



## 例子三

```java
Object obj1 = new Object();
Object obj2 = new Object();
System.out.println(obj1 == obj2);//false
System.out.println(obj1 != obj2);//true
```

```java
 0 new #10 <java/lang/Object>
 3 dup
 4 invokespecial #1 <java/lang/Object.<init> : ()V>
 7 astore_1
 8 new #10 <java/lang/Object>
11 dup
12 invokespecial #1 <java/lang/Object.<init> : ()V>
15 astore_2
16 getstatic #4 <java/lang/System.out : Ljava/io/PrintStream;>
19 aload_1
20 aload_2
21 if_acmpne 28 (+7) // 如果obj1 != obj2
24 iconst_1
25 goto 29 (+4)
28 iconst_0  // false
29 invokevirtual #5 <java/io/PrintStream.println : (Z)V>
32 getstatic #4 <java/lang/System.out : Ljava/io/PrintStream;>
35 aload_1
36 aload_2
37 if_acmpeq 44 (+7)  // 如果 obj1 == obj2
40 iconst_1       // true
41 goto 45 (+4)
44 iconst_0 
45 invokevirtual #5 <java/io/PrintStream.println : (Z)V>
48 return
```

